percula/LICENSE
percula/README.md
percula/__init__.py
percula/cli.py
percula/postprocess.py
percula/preprocess.py
percula/util.py
percula-0.0.5.dist-info/licenses/LICENSE
percula-0.0.5.dist-info/METADATA
percula-0.0.5.dist-info/WHEEL
percula-0.0.5.dist-info/entry_points.txt
percula-0.0.5.dist-info/top_level.txt
percula-0.0.5.dist-info/RECORD
