Metadata-Version: 2.4
Name: percula
Version: 0.0.5
Summary: spaceranger wrangling tools for Oxford Nanopore Technologies' data
Author-email: Oxford Nanopore Technologies <support@nanoporetech.com>
License: Oxford Nanopore Technologies PLC. Public License Version 1.0
Requires-Python: >=3.10
License-File: LICENSE
Requires-Dist: edlib==1.3.9.post1
Requires-Dist: isal==1.7.2
Requires-Dist: msgpack==1.1.0
Requires-Dist: pysam==0.23.1
Requires-Dist: rich==14.0.0
Provides-Extra: dev
Requires-Dist: pytest; extra == "dev"
Requires-Dist: build; extra == "dev"
Requires-Dist: twine; extra == "dev"
Requires-Dist: flake8; extra == "dev"
Requires-Dist: flake8-docstrings; extra == "dev"
Requires-Dist: flake8-rst-docstrings; extra == "dev"
Requires-Dist: flake8-import-order; extra == "dev"
Requires-Dist: flake8-forbid-visual-indent; extra == "dev"
Requires-Dist: pytest; extra == "dev"
Requires-Dist: pytest-cov; extra == "dev"
Requires-Dist: pytest-xdist; extra == "dev"
Dynamic: license-file
